TChatBot/__init__.py
TChatBot/chat.py
TChatBot/config.py
TChatBot/funcs.py
TChatBot/generate.py
TChatBot/main.py
TChatBot/model.py
TChatBot/train.py
TChatBot/input/classes.txt
TChatBot/input/data.pickle
TChatBot/input/intents.json
TChatBot/saved_model/model.h5
TChatBot-0.1.0.dist-info/LICENSE
TChatBot-0.1.0.dist-info/METADATA
TChatBot-0.1.0.dist-info/WHEEL
TChatBot-0.1.0.dist-info/entry_points.txt
TChatBot-0.1.0.dist-info/top_level.txt
TChatBot-0.1.0.dist-info/RECORD
