Metadata-Version: 2.1
Name: TChatBot
Version: 0.1.0
Summary: A ChatBot framework to create customizable all purpose Chatbots using NLP, Tensorflow, Speech Recognition
Home-page: https://github.com/deepraj1729/TChatBot
Author: Deepraj Baidya
Author-email: bdeeprajrkm1@gmail.com
License: MIT
Keywords: A Customizable ChatBot framework with Tensorflow,NLP,Speech Recognition
Platform: UNKNOWN
Classifier: Programming Language :: Python :: 3
Classifier: License :: OSI Approved :: MIT License
Classifier: Operating System :: OS Independent
Requires-Dist: tensorflow-cpu (==1.15)
Requires-Dist: numpy (==1.17)
Requires-Dist: nltk (==3.4.5)
Requires-Dist: prettytable (==0.7.2)
Requires-Dist: sklearn (==0.0)
